[
  {
    "uid": "-ODkpoeSzGyrgWqok4YQ",
    "complete": false,
    "name": 0
  },
  {
    "uid": "-ODkpoeTkrVV8c5OBAhm",
    "complete": false,
    "name": 1
  },
  {
    "uid": "-ODkpoeU0lrG0dgOi_vZ",
    "complete": false,
    "name": 2
  },
  {
    "uid": "-ODkpoeVFWrQ1HdqF3vQ",
    "complete": false,
    "name": 3
  },
  {
    "uid": "-ODkpoeWIV4FNLPN_qib",
    "complete": false,
    "name": 4
  },
  {
    "uid": "-ODkpoeXTzZ78y9-_O4O",
    "complete": false,
    "name": 5
  },
  {
    "uid": "-ODkpoeYyCxjmuWomGTP",
    "complete": false,
    "name": 6
  },
  {
    "uid": "-ODkpoeZYhkyv2kxCmxp",
    "complete": false,
    "name": 7
  },
  {
    "uid": "-ODkpoe_uoRwWR8Y_CwX",
    "complete": false,
    "name": 8
  },
  {
    "uid": "-ODkpoeaua97kSp6MqPq",
    "complete": false,
    "name": 9
  },
  {
    "uid": "-ODkpoebjBQyVOGEtIGI",
    "complete": false,
    "name": 10
  },
  {
    "uid": "-ODkpoecpohe7Zn3cPol",
    "complete": false,
    "name": 11
  },
  {
    "uid": "-ODkpoed8WWK9wsI_4Dh",
    "complete": false,
    "name": 12
  },
  {
    "uid": "-ODkpoeeHpf4IeaFfWua",
    "complete": false,
    "name": 13
  },
  {
    "uid": "-ODkpoef_kH1PhZ-Fk9f",
    "complete": false,
    "name": 14
  },
  {
    "uid": "-ODkpoeglfrohBFjx52W",
    "complete": false,
    "name": 15
  },
  {
    "uid": "-ODkpoehpjTKyvO-FxJx",
    "complete": false,
    "name": 16
  },
  {
    "uid": "-ODkpoei6D8nhPirmIoL",
    "complete": false,
    "name": 17
  },
  {
    "uid": "-ODkpoejFsi9_o4LrWmK",
    "complete": false,
    "name": 18
  },
  {
    "uid": "-ODkpoek55r2gyMkDB0t",
    "complete": false,
    "name": 19
  },
  {
    "uid": "-ODkpoelYf7nse7M1_lY",
    "complete": false,
    "name": 20
  },
  {
    "uid": "-ODkpoenGG22zSVRY_Ng",
    "complete": false,
    "name": 21
  },
  {
    "uid": "-ODkpoeod3KBkFk0uzGo",
    "complete": false,
    "name": 22
  },
  {
    "uid": "-ODkpoeod3KBkFk0uzGp",
    "complete": false,
    "name": 23
  },
  {
    "uid": "-ODkpoep3ie6ugUjGgvY",
    "complete": false,
    "name": 24
  },
  {
    "uid": "-ODkpoeqanxBdklSf3ZR",
    "complete": false,
    "name": 25
  },
  {
    "uid": "-ODkpoerz04Jli1j8mp6",
    "complete": false,
    "name": 26
  },
  {
    "uid": "-ODkpoesBMI9vH6JZ2Co",
    "complete": false,
    "name": 27
  },
  {
    "uid": "-ODkpoet3ZybzxKSkeFE",
    "complete": false,
    "name": 28
  },
  {
    "uid": "-ODkpoevxOA83J4NKOkh",
    "complete": false,
    "name": 29
  },
  {
    "uid": "-ODkpoewnejF7P1_3HTC",
    "complete": false,
    "name": 30
  },
  {
    "uid": "-ODkpoexF-HCBRFubKc2",
    "complete": false,
    "name": 31
  },
  {
    "uid": "-ODkpoeyefOqU_-eT9X3",
    "complete": false,
    "name": 32
  },
  {
    "uid": "-ODkpoez7zvUadJEExpp",
    "complete": false,
    "name": 33
  },
  {
    "uid": "-ODkpof-rfLJYwDMxYeo",
    "complete": false,
    "name": 34
  },
  {
    "uid": "-ODkpof02ZOhjxYnHerZ",
    "complete": false,
    "name": 35
  },
  {
    "uid": "-ODkpof1FgEh9LJ6p8CH",
    "complete": false,
    "name": 36
  },
  {
    "uid": "-ODkpof21qFaLGXTpqtc",
    "complete": false,
    "name": 37
  },
  {
    "uid": "-ODkpof35IndxT1oZtny",
    "complete": false,
    "name": 38
  },
  {
    "uid": "-ODkpof4OgUgbW63-jV2",
    "complete": false,
    "name": 39
  },
  {
    "uid": "-ODkpof5CdHn4MQ-HKHk",
    "complete": false,
    "name": 40
  },
  {
    "uid": "-ODkpof6yHuNr-Se-X43",
    "complete": false,
    "name": 41
  },
  {
    "uid": "-ODkpof7_KZLOCcmYl05",
    "complete": false,
    "name": 42
  },
  {
    "uid": "-ODkpof9bGE2mvj1Jutn",
    "complete": false,
    "name": 43
  },
  {
    "uid": "-ODkpofAgWKnw8RtHW9j",
    "complete": false,
    "name": 44
  },
  {
    "uid": "-ODkpofBiRMaK-Rc0Emm",
    "complete": false,
    "name": 45
  },
  {
    "uid": "-ODkpofCp6E_PISV97TZ",
    "complete": false,
    "name": 46
  },
  {
    "uid": "-ODkpofDK32HitY0x4U_",
    "complete": false,
    "name": 47
  },
  {
    "uid": "-ODkpofE2PYltjKJpc87",
    "complete": false,
    "name": 48
  }
]
